{
  "services": [
    {
      "name": "Phoebus layout manager",
      "link": "_phlayout"
    },
    {
      "name": "Phoebus layout manager",
      "link": "_phlayout"
    }
  ],
  "menu": [
    {
      "name": "File",
      "menu": [
        {
          "name": "Load layout...",
          "link": "_loadlayout"
        },
        {
          "name": "Settings...",
          "link": "_settings"
        },
        {
          "name":"Quick settings",
          "menu": [
            {
             "name":"Use shortcuts",
             "link": "_autoramp_shortcut",
             "checkable": true,
             "checked": true
            },
            {
             "name": "Logbook watcher",
             "link": "_logchecker",
             "checkable": true,
             "checked": true
            }
          ]
        },
        {
          "separator": "true"
        },
        {
          "name": "Edit menus",
          "link": "gedit SLconsole_menus.json"
        },
        {
          "name": "Todo-list",
          "link": "gedit /nfs/Linacshare_controlroom/MCR/launcher/todo.txt"
        },
        {
          "separator": "true"
        },
        {
          "name": "Reload menus",
          "link": "_reload"
        },
        {
          "name": "Relaunch this instance",
          "link": "_relaunch",
          "description": "Simply restarts the launcher."
        },
        {
          "name": "Relaunch all instances",
          "link": "_updateall",
          "description": "Sets an update flag for all running instances of Launcher to see."
        },
        {
          "separator": "true"
        },
        {
          "name": "Git repo",
          "link": "firefox https://gitlab.esss.lu.se/accop/pytools/launcher"
        },
        {
          "separator": "true"
        },
        {
          "name": "Quit",
          "link": "_quit",
          "icon": "quit.png"
        }
      ]
    },
    {

      "name": "Phoebus",
      "menu": [
        {
          "name": "Phauncher...",
          "link": "_rephauncher",
          "description":"Phlauncher!"
        },
        {
          "separator": true
        },
        {
          "name": "As last",
          "link": "/usr/local/bin/phoebus"
        },
        {
          "name": "Nav. only",
          "link": "/bin/bash /nfs/Linacshare_controlroom/MCR/launcher/launch.sh layout_Nav_only.memento"
        },
        {
          "separator": true
        },
        {
          "name": "Nav. only with TS2 Olog",
          "link": "/bin/bash launch.sh layout_Nav_only.memento https://gitlab.esss.lu.se/accop/phoebus-apps/configurations/-/raw/main/ts2.ini"
        },
        {
          "separator": true
        },
        {
          "name": "Beam production",
          "link": "/bin/bash /nfs/Linacshare_controlroom/MCR/launcher/launch.sh layout_beam_production.memento"
        },
        {
          "name": "Buncher conditioning",
          "link": "/bin/bash /nfs/Linacshare_controlroom/MCR/launcher/launch.sh layout_MEBT_bunchers.memento"
        },
        {
          "name": "DTL conditioning",
          "link": "/bin/bash /nfs/Linacshare_controlroom/MCR/launcher/launch.sh layout_DTL1_4_conditioning.memento"
        },
        {
          "name": "Annunciator Standalone",
          "icon": "speaker.png",
          "link": "/bin/bash /nfs/Linacshare_controlroom/MCR/launcher/launch.sh layout_annunciator.memento"
        },
        {
          "separator": true
        },
        {
          "name": "Push local layouts",
          "link": "gnome-terminal -- python gitpusher.py"
        },
        {
          "name": "Layouts git repo / README",
          "link": "firefox https://gitlab.esss.lu.se/accop/phoebus-apps/shared-cs-studio-phoebus-layouts"
        }
      ]
    },
    {
      "name": "OP apps",
      "menu": [
        {
          "name": "AFT",
          "link": "gnome-terminal -- /bin/bash /home/operator-mcr/pytools/esslogbook-gui/start.sh"
        },
        {
          "name": "Shift Start/End",
          "link": "gnome-terminal -- /bin/bash /home/operator-mcr/pytools/esslogbook-gui/start-shiftstart.sh"
        },
        {
          "separator": true
        },
        {
          "name": "Open XAL",
          "link": "/bin/bash /usr/local/bin/openxal-launcher.sh"
        },
        {
          "name": "OpenXAL traj.corr",
          "link": "java -DuseDefaultAccelerator=true -Djava.library.path=/opt/openxal-6.4/lib -jar /opt/openxal-6.4/apps/trajectorycorrection.jar"
        },
        {
          "separator": true
        },
        {
          "name": "Spectrogram",
          "link": "python /home/operator-mcr/pytools/spectrogram/launcher.py",
          "description":"Waveform visualizer"
        },
        {
          "name": "Acronym finder",
          "icon":"wtf.png",
          "link": "python /nfs/Linacshare_controlroom/MCR/CROps/pyabbrdict/ESSdict.py --tk",
          "description":"Check acronyms here"
        },
        {
          "separator": true
        },        

        {
          "name":"Filament heater",
          "menu": [
            {
             "name": "Filament heater...",
             "icon": "filheat.png",
             "link": "gnome-terminal -- python \"/nfs/Linacshare_controlroom/MCR/scripts/filament-heater/fil_start.py\"",
             "arguments": "manual",
             "help_arg": "-h",
             "mandatory_arg": "-p",
             "default_args": "-k RFQ,DTL1,DTL2,DTL3,DTL4 5.30",
             "description":"Start filament heating at predefined time (or now), example: \n fil_heat.py -k RFQ,DTL1 5.30"
            },
            {
              "separator": true
            },
            {
             "name": "NCL: ALL at 6:30",
             "link": "gnome-terminal -- python /nfs/Linacshare_controlroom/MCR/scripts/filament-heater/fil_start.py -k RFQ,DTL1,DTL2,DTL3,DTL4 6.30"
            },
            {
             "name": "NCL: ALL at 7:30",
             "link": "gnome-terminal -- python /nfs/Linacshare_controlroom/MCR/scripts/filament-heater/fil_start.py -k RFQ,DTL1,DTL2,DTL3,DTL4 7.30"
            },
            {
             "name": "NCL: ALL, NOW",
             "link": "gnome-terminal -- python /nfs/Linacshare_controlroom/MCR/scripts/filament-heater/fil_start.py -k RFQ,DTL1,DTL2,DTL3,DTL4 NOW"
            }
          ]
        },
        {
          "name":"Buncher cleaner",
          "menu": [
            {
             "name": "Cleaner...",
             "link": "gnome-terminal -- python \"/nfs/Linacshare_controlroom/MCR/scripts/buncher-cleaner/bunch.py\"",
             "arguments": "manual",
             "help_arg": "-h",
             "mandatory_arg": "",
             "default_args": "-b 1,2,3 -d [-10000,10000,4000] -p 0.05,0.1,0.2,0.5,0.75,1,1.5,2,2.5,3,4,5,6,7",
             "description":"Buncher cleaner with all the options"
            },
            {
              "separator": true
            },
            {
             "name": "10 min HotSpot [beta]...",
             "link": "gnome-terminal -- python \"/nfs/Linacshare_controlroom/MCR/scripts/buncher-cleaner/bunch.py\"",
             "arguments": "manual",
             "help_arg": "-h",
             "mandatory_arg": "-u",
             "default_args": "-b 1,2,3",
             "description":"Just select bunchers, and go!"
            },
            {
             "name": "30 min FastClean...",
             "link": "gnome-terminal -- python \"/nfs/Linacshare_controlroom/MCR/scripts/buncher-cleaner/bunch.py\"",
             "arguments": "manual",
             "help_arg": "-h",
             "mandatory_arg": "-f",
             "default_args": "-b 1,2,3",
             "description":"Just select bunchers, and go!"
            },
            {
             "name": "LongClean...",
             "link": "gnome-terminal -- python \"/nfs/Linacshare_controlroom/MCR/scripts/buncher-cleaner/bunch.py\"",
             "arguments": "manual",
             "help_arg": "-h",
             "mandatory_arg": "",
             "default_args": "-b 1,2,3",
             "description":"The standard cleaning routine for those with time on their hands"
            }
          ]
        },
        {
          "name":"RF shutdown",
          "menu": [
            {
             "name": "Shutdown...",
             "link": "gnome-terminal -- python \"/nfs/Linacshare_controlroom/MCR/scripts/RF_shutdown/shutdown.py\"",
             "arguments": "manual",
             "help_arg": "-h",
             "mandatory_arg": "-p",
             "default_args": "RFQ,DTL1,DTL2,DTL3,DTL4,B1,B2,B3 AUX",
             "description":"Commandline application. \nSelect which klystrons and bunchers to bring to which end state."
            },
            {
              "separator": true
            },
            {
             "name": "NCL: ALL to FIL",
             "icon":"RF.png",
             "link": "gnome-terminal -- python /nfs/Linacshare_controlroom/MCR/scripts/RF_shutdown/shutdown.py RFQ,DTL1,DTL2,DTL3,DTL4,B1,B2,B3 FIL",
             "description":"All bunchers and klystrons to FIL state"
            },
            {
             "name": "NCL: ALL to AUX",
             "link": "gnome-terminal -- python /nfs/Linacshare_controlroom/MCR/scripts/RF_shutdown/shutdown.py RFQ,DTL1,DTL2,DTL3,DTL4,B1,B2,B3 AUX",
             "description":"All bunchers and klystrons to AUX state"
            }
          ]
        },
        {
          "name": "Post Mortem [pre-alpha]",
          "link": "python /nfs/Linacshare_controlroom/MCR/scripts/PMA/pma.py",
          "description": "RF post mortem analyzer [pre-alpha]"
        },
        {
          "name":"RFQ cleaner",
          "menu": [
            {
             "name": "Continue from last",
             "link": "gnome-terminal -- python /nfs/Linacshare_controlroom/MCR/scripts/RFQ_cleaner/RFQ.py",
             "description":"Multipaction cleaning of RFQ\nStart wherever previous run stopped [default]"
            },
            {
             "name": "Start from bottom",
             "link": "gnome-terminal -- python /nfs/Linacshare_controlroom/MCR/scripts/RFQ_cleaner/RFQ.py -f",
             "description":"Multipaction cleaning of RFQ\nForce fresh start"
            }
          ]
        },
        {
          "separator": true
        },
        {
          "name": "Auto-ramp [Ctrl-F12]",
          "link": "python /nfs/Linacshare_controlroom/MCR/scripts/autoramp/autoramp.py",
          "description": "Automatic ramping",
          "shortcut": "Ctrl F12"
        }
      ]
    },
    {
      "name": "Weblinks",
      "menu": [
        {
          "name": "Firefox",
          "icon":"firefox.png",
          "link": "firefox"
        },
        {
          "separator": true
        },
        {
          "name": "Olog",
          "link": "firefox https://olog.esss.lu.se/"
        },
        {
          "name": "Jupyter",
          "icon": "jupyter.png",
          "link": "firefox https://jupyterhub.tn.esss.lu.se/"
        },
        {
          "name": "Confluence OP",
          "link": "firefox https://confluence.esss.lu.se/display/AO/Control+Room+Operations+Group+Home+Page"
        },
        {
          "name": "BETS",
          "link": "firefox https://confluence.esss.lu.se/pages/viewpage.action?pageId=435990027"
        },
        {
          "name": "CR Handbook",
          "link": "firefox https://confluence.esss.lu.se/display/AO/Handbook+for+Control+Room+Operations+Group"
        },
        {
          "name": "Site map",
          "link": "firefox https://confluence.esss.lu.se/display/CER/PPE+on+ESS+Site?preview=/389345968/411750652/ESS%20map%20coloured%20safety%20areas%202022-06-21.jpg"
        },
        {
          "separator": true
        },
        {
          "name": "ISrc RFPM FW",
          "link": "firefox http://isrc-rfpm-fw.tn.esss.lu.se/"
        },
        {
          "name": "ISrc RFPM REF",
          "link": "firefox http://isrc-rfpm-ref.tn.esss.lu.se/"
        },
        {
          "separator": true
        },
        {
          "name": "GitLab",
          "icon":"gitlab.png",
          "link": "firefox https://gitlab.esss.lu.se/accop/"
        },
        {
          "name": "CE-deploy",
          "link": "firefox https://ce-deploy.esss.lu.se"
        },
        {
          "name": "Jira NSOI",
          "link": "firefox https://jira.esss.lu.se/projects/NSOI"
        },
        {
          "name": "Naming service",
          "link": "firefox https://naming.esss.lu.se"
        },
        {
          "name": "Web-Mail",
          "link": "firefox https://mail.esss.lu.se"
        },
        {
          "name": "Public Operations Screen",
          "link": "firefox https://pos.ess.eu/"
        },
        {
          "separator": true
        },
        {
          "name": "Archiver (scalars)",
          "icon":"archive.png",
          "link": "firefox http://archiver-linac-01.tn.esss.lu.se:17665/mgmt/ui/index.html"
        },
        {
          "name": "Archiver (waveforms)",
          "link": "firefox http://archiver-linac-wf-01.tn.esss.lu.se:17665/mgmt/ui/index.html"
        },
        {
          "name": "Archiver Viewer (waveforms)",
          "link": "firefox http://archiver-linac-wf-01.tn.esss.lu.se:17668/retrieval/ui/viewer/archViewer.html"
        },
        {
          "name": "PV search",
          "link": "firefox https://pos.ess.eu/pvs/"
        },
        {
          "name": "Shifter",
          "link": "firefox https://shifter.esss.lu.se/"
        }
      ]
    },
    {
      "name": "Tools",
      "menu": [
        {
          "name": "Calculator",
          "icon":"calc.png",
          "link": "/bin/gnome-calculator"
        },
        {
          "name": "x-kill",
          "link": "xkill",
          "icon": "crosshair.png",
          "description": "Point on any window to kill its creator. Use with caution."
        },
        {
          "name": "Screenshot",
          "link": "gnome-screenshot -i"
        },
        {
          "name": "gedit",
          "link": "gedit"
        },
        {
          "name": "NVIDIA settings",
          "link": "nvidia-settings"
        },
        {
          "separator": true
        },
        {
          "name": "PVmon (simple)",
          "arguments": "manual",
          "link": "gnome-terminal -- /nfs/Linacshare_controlroom/MCR/monitor.sh"
        },
        {
          "name": "PVmon (shiny)",
          "link": "python /nfs/Linacshare_controlroom/MCR/scripts/PVmon/main.py"
        },
        {
          "name": "Reminder",
          "link": "gnome-terminal -- sh -c 'python /nfs/Linacshare_controlroom/MCR/Bilal/reminder.py;echo Press any key to exit;read'",
          "description": "Advanced cognitive time-domain reinforcement technology"
        },
        {
          "separator": true
        },
        {
          "name": "Wallscreen West",
          "link": "/usr/NX/bin/nxplayer /nfs/Linacshare_controlroom/MCR/CROps/WallscreenWest.nxs",
          "description": "NoMachine to MCR wallscreen window side"
        },
        {
          "name": "Wallscreen East",
          "link": "/usr/NX/bin/nxplayer /nfs/Linacshare_controlroom/MCR/CROps/WallscreenEast.nxs",
          "description": "NoMachine to MCR wallscreen target side"
        }
      ]
    },
    {
      "name": "ER",
      "menu": [
        {
          "name": "KLARA",
          "link": "firefox https://secure.port.se/Alphaquest/app_ess/pcmain.cfm?verkid=!%230%20%20%0A"
        },
        {
          "name": "Weather station",
          "icon": "weather.png",
          "link": "firefox https://telegraph.tn.esss.lu.se/public-dashboards/c682f7caf6e4402ab9e1431bbac051c1?orgId=5"
        },
        {
          "name": "On-call",
          "link": "firefox https://confluence.esss.lu.se/display/AO/On+call"
        },
        {
          "separator": true
        },
        {
          "name": "Site map",
          "link": "firefox https://confluence.esss.lu.se/display/CER/PPE+on+ESS+Site?preview=/389345968/411750652/ESS%20map%20coloured%20safety%20areas%202022-06-21.jpg"
        },
        {
          "name": "OP ER procedures",
          "link": "firefox https://confluence.esss.lu.se/display/AO/Emergency+Procedures"
        },
        {
          "name": "How to use Klara",
          "link": "firefox https://confluence.esss.lu.se/display/AO/KLARA+for+Ops"
        }
      ]
    },
    {
      "name": "Docs",
      "menu": [
        {
          "name": "Olog markdown reference",
          "link": "firefox https://olog.esss.lu.se/Olog/help/CommonmarkCheatsheet"
        },
        {
          "separator": true
        },
        {
          "name": "RF block diagrams",
          "link": "firefox https://chess.esss.lu.se/enovia/link/21308.51166.25345.1735"
        },
        {
          "name": "Tech. description NCL",
          "link": "firefox https://chess.esss.lu.se/enovia/link/ESS-0159957/21308.51166.27638.56110/valid"
        },
        {
          "name": "Physics for technical staff",
          "link": "firefox https://chess.esss.lu.se/enovia/link/ESS-1941204/21308.51166.25088.35432/valid"
        }
      ]
    },
    {
      "separator":true
    },
    {
      "name": "PVmon",
      "link": "python /nfs/Linacshare_controlroom/MCR/scripts/PVmon/main.py"
    },
    {
      "name": "Shell",
      "link": "gnome-terminal"
    },
    {
      "name": "Phauncher...",
      "link": "_rephauncher",
      "description":"Phlauncher!"
    }
  ]
}
